pdfTableJson/__init__.py
pdfTableJson/col.py
pdfTableJson/converter.py
pdfTableJson/converter2.py
pdfTableJson/converter_copy.py
pdfTableJson/converter_normal.py
pdfTableJson/group_parser.py
pdfTableJson/merge.py
pdfTableJson/parse.py
pdfTableJson/parse_local.py
pdfTableJson/parser.py
pdfTableJson/plus_data.py
pdfTableJson/row.py
pdfTableJson/util.py
pdfTableJson-2.0.1.dist-info/LICENSE
pdfTableJson-2.0.1.dist-info/METADATA
pdfTableJson-2.0.1.dist-info/WHEEL
pdfTableJson-2.0.1.dist-info/top_level.txt
pdfTableJson-2.0.1.dist-info/zip-safe
pdfTableJson-2.0.1.dist-info/RECORD
