Metadata-Version: 2.1
Name: pdfTableJson
Version: 2.0.1
Summary: UNKNOWN
Home-page: https://github.com/yousojeong/pdfTableJson/
Author: hielosan
Author-email: hielosan@naver.com
License: GNU AFFERO GPL 3.0
Project-URL: Bug Tracker, https://github.com/yousojeong/pdfTableJson/issues
Keywords: pdf,table,json,converter,cv,openCV
Platform: UNKNOWN
Classifier: Programming Language :: Python :: 3.8
Classifier: License :: OSI Approved :: GNU Affero General Public License v3 or later (AGPLv3+)
Requires-Python: >=3.8
License-File: LICENSE
Requires-Dist: opencv-python
Requires-Dist: numpy
Requires-Dist: PyMuPDF
Requires-Dist: pdfTableJson
